Workbook

Sheet Supuestos
A1: PROMACO · Supuestos del presupuesto
A2: Leyenda: celdas AMARILLAS con texto AZUL = datos que usted debe confirmar o reemplazar. Texto negro = fórmulas (no editar). Texto verde = valores traídos de otra hoja. Pase el mouse sobre las celdas con triángulo rojo para ver la explicación.
A4: Supuesto | B4: Valor | C4: Fuente / cómo se obtuvo
A5: Tarifa del desarrollador
A6: Salario mensual de referencia, desarrollador junior (L.) | B6: 20000 | C6: ESTIMADO. Confirmar con 2–3 ofertas reales de Computrabajo / Tecoloco Honduras (anotar fecha y enlace).
A7: Horas laborales por mes | B7: 160 | C7: 40 h/semana × 4 semanas.
A8: Factor de prestaciones laborales | B8: 1 | C8: 1.00 = tarifa de trabajador independiente (sin prestaciones).
A9: Tarifa por hora (L./h) | B9: =B6/B7*B8 -> 125 | C9: Salario ÷ horas al mes × factor.
A11: Porcentajes estándar
A12: Contingencia sobre el subtotal | B12: 0.1 | C12: Criterio usual de gestión de proyectos (5–15 %).
A13: Soporte y mantenimiento anual (% del desarrollo) | B13: 0.15 | C13: Criterio usual de la industria: 15–20 % anual del costo de desarrollo.
A14: Tipo de cambio (L. por US$) | B14: 26.5 | C14: ESTIMADO. Confirmar con el tipo de cambio de referencia del Banco Central de Honduras (bch.hn) el día del presupuesto.
A16: Situación actual (sin sistema) — para la recuperación
A17: Herramientas perdidas al año sin responsable (unidades) | B17: 3 | C17: ESTIMADO. Preguntar a bodega de PROMACO cuántas piezas desaparecieron el último año.
A18: Valor promedio de una herramienta perdida (L.) | B18: 3500 | C18: ESTIMADO. Promedio del precio de reposición de las herramientas que más se pierden (cotizar en ferretería).
A19: Horas al mes dedicadas al control manual (papel / Excel) | B19: 12 | C19: ESTIMADO. Preguntar al encargado de bodega cuánto tiempo invierte en buscar y anotar préstamos.
A20: Salario mensual del encargado de bodega (L.) | B20: 13000 | C20: ESTIMADO. Usar el salario real del puesto o el salario mínimo vigente del sector como piso.
A21: Reparaciones/daños no cobrados al año (L.) | B21: 5000 | C21: ESTIMADO. Daños que hoy nadie registra ni asigna a un responsable.

Sheet Presupuesto
A1: PROMACO · Sistema de Control de Herramientas — Presupuesto de costos (L.)
A2: Total = Cantidad × Costo unitario. Las tarifas por hora vienen de la hoja Supuestos (texto verde).
A4: Rubro | B4: Detalle | C4: Cantidad | D4: Unidad | E4: Costo unitario (L.) | F4: Total (L.) | G4: Fuente / justificación
A5: 1. Desarrollo
B6: Análisis y requisitos | C6: 40 | D6: horas | E6: =Supuestos!$B$9 -> 125 | F6: =C6*E6 -> 5000 | G6: Horas estimadas del proyecto (mar–oct 2026).
B7: Diseño de base de datos | C7: 40 | D7: horas | E7: =Supuestos!$B$9 -> 125 | F7: =C7*E7 -> 5000 | G7: Horas estimadas. Ver docs/diagrama-er.md.
B8: Diseño de interfaz | C8: 40 | D8: horas | E8: =Supuestos!$B$9 -> 125 | F8: =C8*E8 -> 5000 | G8: Horas estimadas. Ver docs/diseno-interfaz.md.
B9: Programación de la aplicación (C# / WinForms) | C9: 260 | D9: horas | E9: =Supuestos!$B$9 -> 125 | F9: =C9*E9 -> 32500 | G9: Horas estimadas; el sistema tiene ~12,700 líneas de C# propias.
B10: Base de datos: procedimientos, vistas y migraciones (SQL) | C10: 120 | D10: horas | E10: =Supuestos!$B$9 -> 125 | F10: =C10*E10 -> 15000 | G10: Horas estimadas; ~7,800 líneas de SQL (instalación + 18 migraciones).
B11: Pruebas y corrección de errores | C11: 60 | D11: horas | E11: =Supuestos!$B$9 -> 125 | F11: =C11*E11 -> 7500 | G11: Horas estimadas.
B12: Documentación y manual | C12: 40 | D12: horas | E12: =Supuestos!$B$9 -> 125 | F12: =C12*E12 -> 5000 | G12: Horas estimadas.
B13: Subtotal desarrollo | F13: =SUM(F6:F12) -> 75000
A15: 2. Licencias
B16: .NET 10 y Visual Studio Community | C16: 1 | D16: licencia | E16: 0 | F16: =C16*E16 -> 0 | G16: Gratuitos (Microsoft). Community permitido para equipos pequeños.
B17: SQL Server Express | C17: 1 | D17: licencia | E17: 0 | F17: =C17*E17 -> 0 | G17: Gratuito hasta 10 GB por base de datos; suficiente para el inventario.
B18: ClosedXML, FontAwesome.Sharp, SqlClient, Newtonsoft.Json | C18: 1 | D18: paquete | E18: 0 | F18: =C18*E18 -> 0 | G18: Licencia MIT: uso comercial libre.
B19: Librería PDF (iText 9) | C19: 1 | D19: licencia | E19: 0 | F19: =C19*E19 -> 0 | G19: PENDIENTE: iText es AGPL. Opción A: reemplazar por QuestPDF/PdfSharp (L. 0). Opción B: licencia comercial (cotizar en US$ y multiplicar por el tipo de cambio).
B20: Windows en las estaciones | C20: 1 | D20: licencia | E20: 0 | F20: =C20*E20 -> 0 | G20: Equipos existentes de PROMACO ya tienen Windows.
B21: Subtotal licencias | F21: =SUM(F16:F20) -> 0
A23: 3. Hardware
B24: Computadora servidor / estación principal | C24: 1 | D24: equipo | E24: 0 | F24: =C24*E24 -> 0 | G24: Se reutiliza equipo existente de PROMACO. Si no hay, cotizar en 2–3 tiendas.
B25: Disco externo para respaldos (1 TB) | C25: 1 | D25: unidad | E25: 1500 | F25: =C25*E25 -> 1500 | G25: ESTIMADO. Reemplazar por cotización real (tienda, fecha).
B26: UPS / regulador para el equipo con la base de datos | C26: 1 | D26: unidad | E26: 2000 | F26: =C26*E26 -> 2000 | G26: ESTIMADO. Reemplazar por cotización real (tienda, fecha).
B27: Etiquetas para identificar cada unidad (HER-0001-03) | C27: 1 | D27: lote | E27: 800 | F27: =C27*E27 -> 800 | G27: ESTIMADO. Etiquetas adhesivas resistentes o placas; cotizar.
B28: Subtotal hardware | F28: =SUM(F24:F27) -> 4300
A30: 4. Implementación
B31: Instalación de SQL Server y la aplicación | C31: 8 | D31: horas | E31: =Supuestos!$B$9 -> 125 | F31: =C31*E31 -> 1000 | G31: Horas estimadas.
B32: Carga inicial del inventario y etiquetado | C32: 24 | D32: horas | E32: =Supuestos!$B$9 -> 125 | F32: =C32*E32 -> 3000 | G32: Horas estimadas; depende de cuántas herramientas tenga PROMACO.
B33: Capacitación de operadores y administradores | C33: 8 | D33: horas | E33: =Supuestos!$B$9 -> 125 | F33: =C33*E33 -> 1000 | G33: Horas estimadas.
B34: Subtotal implementación | F34: =SUM(F31:F33) -> 5000
B36: Subtotal general | F36: =F13+F21+F28+F34 -> 84300
B37: Contingencia | E37: =Supuestos!$B$12 -> 0.1 | F37: =F36*E37 -> 8430 | G37: Imprevistos, sobre el subtotal general.
B38: TOTAL INVERSIÓN INICIAL | F38: =F36+F37 -> 92730
B40: Soporte y mantenimiento anual (recurrente) | E40: =Supuestos!$B$13 -> 0.15 | F40: =F13*E40 -> 11250 | G40: Porcentaje anual sobre el subtotal de desarrollo. No forma parte de la inversión inicial.
B42: Horas totales de desarrollo | F42: =SUMIFS(C5:C12,D5:D12,"horas") -> 600

Sheet Recuperación
A1: PROMACO · ¿En cuánto tiempo se paga el sistema?
A3: Concepto | B3: Monto (L.) | C3: Cálculo
A4: Pérdida anual por herramientas extraviadas | B4: =Supuestos!B17*Supuestos!B18 -> 10500 | C4: Unidades perdidas × valor promedio.
A5: Costo anual del control manual | B5: =Supuestos!B19*12*Supuestos!B20/Supuestos!B7 -> 11700 | C5: Horas al mes × 12 × costo por hora del encargado.
A6: Daños no cobrados al año | B6: =Supuestos!B21 -> 5000 | C6: Tomado de Supuestos.
A7: Ahorro anual estimado con el sistema | B7: =SUM(B4:B6) -> 27200 | C7: Supone que el sistema evita estas pérdidas. Sea conservador: puede multiplicar por 50–70 %.
A8: Costo anual de soporte | B8: =Presupuesto!F40 -> 11250 | C8: Desde Presupuesto.
A9: Beneficio neto anual | B9: =B7-B8 -> 15950 | C9: Ahorro − soporte.
A10: Inversión inicial | B10: =Presupuesto!F38 -> 92730 | C10: Desde Presupuesto.
A11: Meses para recuperar la inversión | B11: =IF(B9>0,B10/B9*12,"No se recupera") -> 69.765517 | C11: Inversión ÷ beneficio neto anual × 12.

Sheet Notas para Claude
A1: NOTAS PARA CLAUDE (y para cualquier revisor)
A2: Esta hoja da contexto a Claude para ayudar al autor a completar y defender el presupuesto. El autor no tiene experiencia poniendo precio a su trabajo: explicar cada número en lenguaje sencillo.
A4: Contexto del proyecto
A5: • PROMACO es una empresa real en Honduras. Moneda: lempiras (L.). Todo cálculo final debe quedar en L.
A6: • Sistema de escritorio C# / .NET 10 (WinForms) + SQL Server; repositorio PromacoHerra. Proyecto académico aprobado el 2026-10-05.
A7: • Desarrollo del 2026-03-16 al 2026-10 (≈ 7 meses, medio tiempo). ~12,700 líneas de C# propias y ~7,800 de SQL.
A8: • Las horas por fase (Presupuesto, columna C) son ESTIMADAS (~600 h ≈ 20 h/semana). Si el autor recuerda sus horas reales, usarlas.
A10: Cómo está armado el libro
A11: • Supuestos: todas las entradas (amarillo/azul). Cambiar un valor ahí actualiza todo el libro; nunca escribir números dentro de fórmulas.
A12: • Presupuesto: Total = Cantidad × Costo unitario. Las partidas en horas toman la tarifa de Supuestos!B9 (= salario ÷ horas × factor).
A13: • Recuperación: compara el ahorro anual estimado contra la inversión y calcula los meses para recuperarla.
A15: Pendientes para completar con el autor
... A26: • Ser conservador en la Recuperación: un evaluador confía más en ahorros modestos bien justificados.
